{"Response": "Success", "Message": "", "HasWarning": false, "Type": 100, "RateLimit": {}, "Data": {"RAW": {"NEAR": {"BNB": {"CCSEQ": 12067876, "BID": 0.00694, "ASK": 0.00698}, "USDT": {"CCSEQ": 57592119, "BID": 2.0076, "ASK": 2.0088}, "BUSD": {"CCSEQ": 16788476, "BID": 2.0058, "ASK": 2.0116}, "BTC": {"CCSEQ": 62085, "BID": 6e-05, "ASK": 6.01e-05}}}, "DISPLAY": {"NEAR": {"BNB": {"BID": "BNB 0.006940", "ASK": "BNB 0.006980"}, "USDT": {"BID": "\u20ae 2.01", "ASK": "\u20ae 2.01"}, "BUSD": {"BID": "BUSD 2.01", "ASK": "BUSD 2.01"}, "BTC": {"BID": "\u0243 0.00006000", "ASK": "\u0243 0.00006010"}}}}}