{"Response": "Success", "Message": "", "HasWarning": false, "Type": 100, "RateLimit": {}, "Data": {"RAW": {"QTUM": {"BTC": {"CCSEQ": 24319079, "BID": 0.0002125, "ASK": 0.0002128}, "ETH": {"CCSEQ": 27430193, "BID": 0.003353, "ASK": 0.003363}, "USDT": {"CCSEQ": 52909746, "BID": 7.115, "ASK": 7.123}, "BUSD": {"CCSEQ": 21316652, "BID": 7.111, "ASK": 7.123}, "BNB": {"CCSEQ": 58}}}, "DISPLAY": {"QTUM": {"BTC": {"BID": "\u0243 0.0002125", "ASK": "\u0243 0.0002128"}, "ETH": {"BID": "\u039e 0.003353", "ASK": "\u039e 0.003363"}, "USDT": {"BID": "\u20ae 7.12", "ASK": "\u20ae 7.12"}, "BUSD": {"BID": "BUSD 7.11", "ASK": "BUSD 7.12"}, "BNB": {}}}}}