{"Response": "Success", "Message": "", "HasWarning": false, "Type": 100, "RateLimit": {}, "Data": {"RAW": {"YFII": {"BUSD": {"CCSEQ": 35083, "BID": 1938.76, "ASK": 1944.86}, "BTC": {"CCSEQ": 42089889, "BID": 0.05795, "ASK": 0.05809}, "USDT": {"CCSEQ": 89267798, "BID": 1940.35, "ASK": 1943.33}, "BNB": {"CCSEQ": 24904338, "BID": 6.713, "ASK": 6.743}}}, "DISPLAY": {"YFII": {"BUSD": {"BID": "BUSD 1,938.76", "ASK": "BUSD 1,944.86"}, "BTC": {"BID": "\u0243 0.05795", "ASK": "\u0243 0.05809"}, "USDT": {"BID": "\u20ae 1,940.35", "ASK": "\u20ae 1,943.33"}, "BNB": {"BID": "BNB 6.71", "ASK": "BNB 6.74"}}}}}